heiya/__init__.py
heiya/convert.py
heiya/extensions.py
heiya/from_hei.py
heiya/meta_transfer.py
heiya/to_hei.py
heiya/tools.py
heiya-2.3.1.dist-info/LICENSE.txt
heiya-2.3.1.dist-info/METADATA
heiya-2.3.1.dist-info/WHEEL
heiya-2.3.1.dist-info/top_level.txt
heiya-2.3.1.dist-info/RECORD
