Metadata-Version: 2.1
Name: heiya
Version: 2.3.1
Summary: Convert between image and High Efficiency Image (HEIC/AVIF) with ease.
Home-page: https://github.com/wu-hongjun/heiya
Download-URL: https://pypi.org/project/heiya/
Author: Hongjun Wu
Author-email: hw434@cornell.edu
License: Apache License 2.0
Keywords: HEIC,AVIF,TIFF,JPG,ImageConversion
License-File: LICENSE.txt
Requires-Dist: piexif
Requires-Dist: pillow-heif
Requires-Dist: pyperclip
Requires-Dist: pathlib
Requires-Dist: Pillow
